fair_debate_md/__init__.py
fair_debate_md/cli.py
fair_debate_md/core.py
fair_debate_md/key_management.py
fair_debate_md/release.py
fair_debate_md/repo_handling.py
fair_debate_md/utils.py
fair_debate_md/fixtures/README.md
fair_debate_md/fixtures/__init__.py
fair_debate_md/fixtures/txt1.md
fair_debate_md/fixtures/txt1_debug.html
fair_debate_md/fixtures/txt1_debug_rk.md
fair_debate_md/fixtures/__pycache__/__init__.cpython-311.pyc
fair_debate_md/fixtures/repo-preparation/README.md
fair_debate_md/fixtures/repo-preparation/d00-explanatory-example-debate__plain/a/a.md
fair_debate_md/fixtures/repo-preparation/d00-explanatory-example-debate__plain/a/a14b12a.md
fair_debate_md/fixtures/repo-preparation/d00-explanatory-example-debate__plain/a/a14b15a.md
fair_debate_md/fixtures/repo-preparation/d00-explanatory-example-debate__plain/a/a14b6a.md
fair_debate_md/fixtures/repo-preparation/d00-explanatory-example-debate__plain/b/a14b.md
fair_debate_md/fixtures/repo-preparation/d00-explanatory-example-debate__plain/b/a15b.md
fair_debate_md/fixtures/repo-preparation/d00-explanatory-example-debate__plain/b/a20b.md
fair_debate_md/fixtures/repos/d00-explanatory-example-debate/patches_01/0001-automatic-contribution.patch
fair_debate_md/fixtures/repos/d00-explanatory-example-debate/patches_01/0002-automatic-contribution.patch
fair_debate_md/fixtures/repos/d00-explanatory-example-debate/patches_01/0003-automatic-contribution.patch
fair_debate_md/fixtures/repos/d02-test_debate/patches_01/0001-first-commit.patch
fair_debate_md/fixtures/repos/d02-test_debate/patches_01/0002-add-contribution-a-a.md.patch
fair_debate_md/fixtures/repos/d02-test_debate/patches_01/0003-add-contribution-b-a14b.md.patch
fair_debate_md/fixtures/repos/d03-test_debate/patches_01/0001-first-commit.patch
fair_debate_md/fixtures/repos/d03-test_debate/patches_01/0002-add-contribution-a-a.md.patch
fair_debate_md/fixtures/repos/d03-test_debate/patches_01/0003-add-contribution-b-a14b.md.patch
fair_debate_md-0.5.1.dist-info/METADATA
fair_debate_md-0.5.1.dist-info/WHEEL
fair_debate_md-0.5.1.dist-info/entry_points.txt
fair_debate_md-0.5.1.dist-info/top_level.txt
fair_debate_md-0.5.1.dist-info/RECORD
