Metadata-Version: 2.4
Name: fair_debate_md
Version: 0.5.1
Requires-Python: >=3.11
Requires-Dist: ipydex
Requires-Dist: markdown
Requires-Dist: markdownify>=0.13
Requires-Dist: bs4
Requires-Dist: gitpython
